mpbroker/__init__.py
mpbroker/__main__.py
mpbroker/config/__init__.py
mpbroker/config/config.py
mpbroker/config/db_init_design_docs.py
mpbroker/config/models.py
mpbroker/example/user_config.toml
mpbroker/main.py
mpbroker/models/__init__.py
mpbroker/models/ingest.py
mpbroker/models/media.py
mpbroker/tools.py
mpbroker/utils.py
mpbroker-1.1.0.dist-info/LICENSE
mpbroker-1.1.0.dist-info/METADATA
mpbroker-1.1.0.dist-info/WHEEL
mpbroker-1.1.0.dist-info/entry_points.txt
mpbroker-1.1.0.dist-info/RECORD
