Metadata-Version: 2.1
Name: mpbroker
Version: 1.1.0
Summary: Media Player Broker
Home-page: https://gitlab.com/drad/mpbroker
License: GPL-3.0-only
Keywords: media player,broker,player,video,smplayer,vlc,couchdb,cli,mpv
Author: drad
Author-email: sa@adercon.com
Maintainer: drad
Maintainer-email: sa@adercon.com
Requires-Python: >=3.11,<4.0
Classifier: License :: OSI Approved :: GNU General Public License v3 (GPLv3)
Classifier: Programming Language :: Python :: 3
Classifier: Programming Language :: Python :: 3.11
Classifier: Programming Language :: Python :: 3.12
Requires-Dist: natsort (>=8.4,<9.0)
Requires-Dist: pycouchdb (>=1.16,<2.0)
Requires-Dist: pydantic (>=2.7,<3.0)
Requires-Dist: pymediainfo (>=6.1,<7.0)
Requires-Dist: requests (>=2.32,<3.0)
Requires-Dist: rich (>=13.7,<14.0)
Requires-Dist: typer[all] (>=0.12,<0.13)
Project-URL: Repository, https://gitlab.com/drad/mpbroker
